pgc_interface/__init__.py
pgc_interface/pgc_interface.py
pgc_interface/pythonjsonlogger/__init__.py
pgc_interface/pythonjsonlogger/jsonlogger.py
pgc_interface-1.1.9.dist-info/LICENSE
pgc_interface-1.1.9.dist-info/METADATA
pgc_interface-1.1.9.dist-info/WHEEL
pgc_interface-1.1.9.dist-info/top_level.txt
pgc_interface-1.1.9.dist-info/RECORD
