Metadata-Version: 2.1
Name: pgc-interface
Version: 1.1.9
Summary: PGC Interface
Home-page: https://github.com/UniversalDevicesInc/pgc-python-interface
Author: James Milne
Author-email: milne.james@gmail.com
License: MIT
Platform: UNKNOWN
Classifier: Development Status :: 4 - Beta
Classifier: License :: OSI Approved :: MIT License
Classifier: Programming Language :: Python :: 3.3
Classifier: Programming Language :: Python :: 3.4
Classifier: Programming Language :: Python :: 3.5
Classifier: Programming Language :: Python :: 3.6
Requires-Python: >2.7,!=3.0.*,!=3.1.*,!=3.2.*
Requires-Dist: AWSIoTPythonSDK
